fmcib/__init__.py
fmcib/callbacks/__init__.py
fmcib/callbacks/prediction_saver.py
fmcib/callbacks/utils.py
fmcib/datasets/__init__.py
fmcib/datasets/ssl_radiomics_dataset.py
fmcib/datasets/utils.py
fmcib/models/__init__.py
fmcib/models/autoencoder.py
fmcib/models/load_model.py
fmcib/models/models_genesis.py
fmcib/optimizers/__init__.py
fmcib/optimizers/lars.py
fmcib/preprocessing/__init__.py
fmcib/preprocessing/seed_based_crop.py
fmcib/run.py
fmcib/ssl/__init__.py
fmcib/ssl/losses/__init__.py
fmcib/ssl/losses/neg_mining_info_nce_loss.py
fmcib/ssl/losses/nnclr_loss.py
fmcib/ssl/losses/ntxent_loss.py
fmcib/ssl/losses/ntxent_mined_loss.py
fmcib/ssl/losses/swav_loss.py
fmcib/ssl/modules/__init__.py
fmcib/ssl/modules/exneg_simclr.py
fmcib/ssl/modules/nnclr.py
fmcib/ssl/modules/simclr.py
fmcib/ssl/modules/swav.py
fmcib/transforms/__init__.py
fmcib/transforms/duplicate.py
fmcib/transforms/med3d.py
fmcib/transforms/multicrop.py
fmcib/transforms/random_resized_crop.py
fmcib/utils/__init__.py
fmcib/utils/download_utils.py
fmcib/utils/idc_helper.py
fmcib/visualization/__init__.py
fmcib/visualization/verify_io.py
foundation_cancer_image_biomarker-1.0.0.dist-info/LICENSE
foundation_cancer_image_biomarker-1.0.0.dist-info/METADATA
foundation_cancer_image_biomarker-1.0.0.dist-info/WHEEL
foundation_cancer_image_biomarker-1.0.0.dist-info/RECORD
