Metadata-Version: 2.1
Name: foundation-cancer-image-biomarker
Version: 1.0.0
Summary: Official repo for Foundation Models for Quantitative Biomarker Discovery in Cancer Imaging [INSERT DOI]
Home-page: https://aim.hms.harvard.edu/foundation-cancer-image-biomarker
License: MIT
Author: Suraj Pai
Author-email: bspai@bwh.harvard.edu
Requires-Python: >=3.8,<3.12
Classifier: Development Status :: 3 - Alpha
Classifier: Intended Audience :: Developers
Classifier: License :: OSI Approved :: MIT License
Classifier: Operating System :: OS Independent
Classifier: Programming Language :: Python :: 3
Classifier: Programming Language :: Python :: 3.8
Classifier: Programming Language :: Python :: 3.9
Classifier: Programming Language :: Python :: 3.10
Classifier: Programming Language :: Python :: 3.11
Classifier: Topic :: Software Development :: Libraries :: Python Modules
Requires-Dist: aiohttp (>=3.9.1,<4.0.0)
Requires-Dist: dcmrtstruct2nii (>=5,<6)
Requires-Dist: fonttools (>=4.44.0,<5.0.0)
Requires-Dist: google-cloud-storage (>=2.9.0,<3.0.0)
Requires-Dist: itk (>=5.3.0,<6.0.0)
Requires-Dist: lightly (==1.4.19)
Requires-Dist: matplotlib (>=3.7.1,<4.0.0)
Requires-Dist: mpmath (==1.3.0)
Requires-Dist: nibabel (>=5.1.0,<6.0.0)
Requires-Dist: pip (>=23.3.2,<24.0.0)
Requires-Dist: platipy (==0.4.1)
Requires-Dist: project-lighter (==0.0.2a19)
Requires-Dist: pydantic (==1.10.13)
Requires-Dist: pydicom (>=2.4.0,<3.0.0)
Requires-Dist: pydicom-seg (>=0.4.1,<0.5.0)
Requires-Dist: pynrrd (>=1.0.0,<2.0.0)
Requires-Dist: scipy (==1.10.0)
Requires-Dist: thedicomsort (>=1.0.1,<2.0.0)
Requires-Dist: tornado (>=6.4,<7.0)
Requires-Dist: urllib3 (>=2.1.0,<3.0.0)
Requires-Dist: wandb (>=0.16.3,<0.17.0)
Requires-Dist: werkzeug (>=3.0.1,<4.0.0)
Requires-Dist: wget (>=3.2,<4.0)
Project-URL: Repository, https://github.com/AIM-Harvard/foundation-cancer-image-biomarker
